__init__.py
bibquest.py
bibquest-0.1.2.dist-info/METADATA
bibquest-0.1.2.dist-info/WHEEL
bibquest-0.1.2.dist-info/entry_points.txt
bibquest-0.1.2.dist-info/top_level.txt
bibquest-0.1.2.dist-info/RECORD
