Metadata-Version: 2.4
Name: bibquest
Version: 0.1.2
Summary: A tool to automatically fetch BibTeX entries from ADS, arXiv, and INSPIRE-HEP based on citation keys found in LaTeX log files or documents.
Author: Sahil Jhawar
Project-URL: Homepage, https://github.com/sahiljhawar/BibQuest
Project-URL: Tracker, https://github.com/sahiljhawar/BibQuest/issues
Requires-Python: >=3.9
Requires-Dist: bibtexparser>=1.4.3
Requires-Dist: bs4>=0.0.2
Requires-Dist: requests>=2.32.3
